main.py
henriupton99testuv-0.0.1.dist-info/METADATA
henriupton99testuv-0.0.1.dist-info/WHEEL
henriupton99testuv-0.0.1.dist-info/top_level.txt
henriupton99testuv-0.0.1.dist-info/RECORD
